_bloock_bridge_lib.abi3.so
_bridge/__init__.py
_bridge/bridge.py
_bridge/channel.py
_ffi/__init__.py
_ffi/build.py
_ffi/ffi.py
bloock_sdk-2.0.0b9.dist-info/METADATA
bloock_sdk-2.0.0b9.dist-info/WHEEL
bloock_sdk-2.0.0b9.dist-info/top_level.txt
bloock_sdk-2.0.0b9.dist-info/RECORD
